skwebsocket/__init__.py
skwebsocket/recfile.py
skwebsocket/sendfile.py
skwebsocket/server.py
skwebsocket/test.py
skwebsocket/websocket.py
skwebsocket-0.1.dist-info/LICENSE
skwebsocket-0.1.dist-info/METADATA
skwebsocket-0.1.dist-info/WHEEL
skwebsocket-0.1.dist-info/top_level.txt
skwebsocket-0.1.dist-info/RECORD
