Metadata-Version: 2.1
Name: skwebsocket
Version: 0.1
Summary: A simple WebSocket library for communication between server and client
Home-page: https://github.com/prathaaccount/skwebsocket
Author: soniya
Author-email: prathpatil28@gmail.com
License: UNKNOWN
Platform: UNKNOWN
Classifier: Programming Language :: Python :: 3
Classifier: License :: OSI Approved :: MIT License
Classifier: Operating System :: OS Independent
Requires-Dist: websockets
